{
  "stats": {
    "suites": 1,
    "tests": 22,
    "passes": 4,
    "pending": 0,
    "failures": 18,
    "start": "2024-07-07T00:35:23.492Z",
    "end": "2024-07-07T00:35:26.548Z",
    "duration": 2756,
    "testsRegistered": 22,
    "passPercent": 18.181818181818183,
    "pendingPercent": 0,
    "other": 0,
    "hasOther": false,
    "skipped": 0,
    "hasSkipped": false
  },
  "results": [
    {
      "uuid": "0932939c-93f7-4d82-a8d6-1c8bf370f342",
      "title": "",
      "fullFile": "cypress/integration/uniresolver_spec.js",
      "file": "cypress/integration/uniresolver_spec.js",
      "beforeHooks": [],
      "afterHooks": [],
      "tests": [],
      "suites": [
        {
          "uuid": "ea19c03e-5f14-474a-bbad-711253a2ab45",
          "title": "Test Scenario 1: DID Resolution Result fixtures: https://dev.uniresolver.io/1.0/identifiers/",
          "fullFile": "",
          "file": "",
          "beforeHooks": [],
          "afterHooks": [],
          "tests": [
            {
              "title": "A correct DID can be resolved",
              "fullTitle": "Test Scenario 1: DID Resolution Result fixtures: https://dev.uniresolver.io/1.0/identifiers/ A correct DID can be resolved",
              "timedOut": null,
              "duration": 395,
              "state": "failed",
              "speed": null,
              "pass": false,
              "fail": true,
              "pending": false,
              "context": null,
              "code": "cy.clearCookies();\ncy.fixture(path_example_dids).its(\"normalDids\").then(list => {\n  Object.keys(list).forEach(key => {\n    const normalDid = list[key];\n    cy.request({\n      method: \"GET\",\n      url: endpoint + normalDid,\n      failOnStatusCode: false\n    }).as(\"request\");\n    cy.get(\"@request\").then(response => {\n      expect(response.status).to.eq(200);\n    });\n    cy.get(\"@request\").then(response => {\n      expect(response.headers[\"content-type\"].replace(/\\s+/g, \"\")).contains('application/ld+json;profile=\"https://w3id.org/did-resolution');\n    });\n    cy.get(\"@request\").then(response => {\n      expect(response).to.be.a(\"object\");\n    });\n    cy.get(\"@request\").then(response => {\n      expect(response.body).to.have.property(\"didDocument\");\n    });\n    cy.get(\"@request\").then(response => {\n      expect(response.body).to.have.property(\"didResolutionMetadata\");\n    });\n    cy.get(\"@request\").then(response => {\n      expect(response.body).to.have.property(\"didDocumentMetadata\");\n    });\n    cy.get(\"@request\").then(response => {\n      expect(response.body.didDocument.id).to.be.a(\"string\").and.satisfy(msg => msg.startsWith(\"did:\"));\n    });\n  });\n});",
              "err": {
                "message": "AssertionError: expected 404 to equal 200",
                "estack": "AssertionError: expected 404 to equal 200\n    at Context.eval (http://localhost:40051/__cypress/tests?p=cypress/integration/uniresolver_spec.js:116:40)",
                "diff": "- 404\n+ 200\n"
              },
              "uuid": "3c4dea38-e3fc-41b7-b458-43583eb49bef",
              "parentUUID": "ea19c03e-5f14-474a-bbad-711253a2ab45",
              "isHook": false,
              "skipped": false
            }
          ],
          "suites": [],
          "passes": [],
          "failures": [
            "3c4dea38-e3fc-41b7-b458-43583eb49bef"
          ],
          "pending": [],
          "skipped": [],
          "duration": 395,
          "root": false,
          "rootEmpty": false,
          "_timeout": 2000
        },
        {
          "uuid": "0e2d27de-5814-48a5-9420-e162d3664ad2",
          "title": "Test Scenario 2: JSON-LD DID document",
          "fullFile": "",
          "file": "",
          "beforeHooks": [],
          "afterHooks": [],
          "tests": [
            {
              "title": "A correct DID can be resolved with header input",
              "fullTitle": "Test Scenario 2: JSON-LD DID document A correct DID can be resolved with header input",
              "timedOut": null,
              "duration": 105,
              "state": "failed",
              "speed": null,
              "pass": false,
              "fail": true,
              "pending": false,
              "context": null,
              "code": "cy.fixture(path_example_dids).its(\"normalDids\").then(list => {\n  Object.keys(list).forEach(key => {\n    const normalDid = list[key];\n    cy.request({\n      method: \"GET\",\n      url: endpoint + normalDid,\n      headers: {\n        Accept: \"application/did+ld+json\"\n      },\n      failOnStatusCode: false\n    }).as(\"request\");\n    cy.get(\"@request\").then(response => {\n      expect(response.status).to.eq(200);\n      expect(response.headers[\"content-type\"]).to.contain(\"application/did+ld+json\");\n      cy.get(\"@request\").then(response => {\n        expect(response).to.be.a(\"object\");\n      });\n      expect(response.body).not.to.have.property(\"didDocument\");\n      expect(response.body[\"id\"]).to.contain(normalDid);\n    });\n  });\n});",
              "err": {
                "message": "AssertionError: expected 404 to equal 200",
                "estack": "AssertionError: expected 404 to equal 200\n    at Context.eval (http://localhost:40051/__cypress/tests?p=cypress/integration/uniresolver_spec.js:157:40)",
                "diff": "- 404\n+ 200\n"
              },
              "uuid": "822155fd-95f2-46ef-9e88-1af6f747bed7",
              "parentUUID": "0e2d27de-5814-48a5-9420-e162d3664ad2",
              "isHook": false,
              "skipped": false
            }
          ],
          "suites": [],
          "passes": [],
          "failures": [
            "822155fd-95f2-46ef-9e88-1af6f747bed7"
          ],
          "pending": [],
          "skipped": [],
          "duration": 105,
          "root": false,
          "rootEmpty": false,
          "_timeout": 2000
        },
        {
          "uuid": "86218d16-6ef0-4a56-8e49-23c029acfdb8",
          "title": "Test Scenario 3: Representation not supported",
          "fullFile": "",
          "file": "",
          "beforeHooks": [],
          "afterHooks": [],
          "tests": [
            {
              "title": "Shows an error when a representation is prompted",
              "fullTitle": "Test Scenario 3: Representation not supported Shows an error when a representation is prompted",
              "timedOut": null,
              "duration": 105,
              "state": "failed",
              "speed": null,
              "pass": false,
              "fail": true,
              "pending": false,
              "context": null,
              "code": "cy.fixture(path_example_dids).its(\"normalDids\").then(list => {\n  Object.keys(list).forEach(key => {\n    const normalDid = list[key];\n    cy.request({\n      method: \"GET\",\n      url: endpoint + normalDid,\n      headers: {\n        Accept: \"image/png\"\n      },\n      failOnStatusCode: false\n    }).then(response => {\n      expect(response.status).to.eq(406);\n      console.log(response);\n      expect(response.body.dereferencingMetadata.error).to.eq('\"representationNotSupported\"');\n    });\n  });\n});",
              "err": {
                "message": "TypeError: Cannot read properties of undefined (reading 'error')",
                "estack": "TypeError: Cannot read properties of undefined (reading 'error')\n    at Context.eval (http://localhost:40051/__cypress/tests?p=cypress/integration/uniresolver_spec.js:213:56)",
                "diff": null
              },
              "uuid": "acbd65c1-e7f5-4940-bd7c-8d029b5d4d2c",
              "parentUUID": "86218d16-6ef0-4a56-8e49-23c029acfdb8",
              "isHook": false,
              "skipped": false
            }
          ],
          "suites": [],
          "passes": [],
          "failures": [
            "acbd65c1-e7f5-4940-bd7c-8d029b5d4d2c"
          ],
          "pending": [],
          "skipped": [],
          "duration": 105,
          "root": false,
          "rootEmpty": false,
          "_timeout": 2000
        },
        {
          "uuid": "9fcdf230-5016-47a3-8008-8c044f533da0",
          "title": "Test Scenario 4: Deactivated",
          "fullFile": "",
          "file": "",
          "beforeHooks": [],
          "afterHooks": [],
          "tests": [
            {
              "title": "Returns an HTTP code of 410 for deactivated DIDs",
              "fullTitle": "Test Scenario 4: Deactivated Returns an HTTP code of 410 for deactivated DIDs",
              "timedOut": null,
              "duration": 72,
              "state": "failed",
              "speed": null,
              "pass": false,
              "fail": true,
              "pending": false,
              "context": null,
              "code": "cy.fixture(path_example_dids).its(\"deacDids\").then(list => {\n  Object.keys(list).forEach(key => {\n    const deacDid = list[key];\n    cy.request({\n      method: \"GET\",\n      url: endpoint + deacDid,\n      failOnStatusCode: false\n    }).then(response => {\n      expect(response.status).to.eq(410);\n      expect(response).to.be.a(\"object\");\n      expect(response.headers[\"content-type\"]).to.contain('application/ld+json;profile=\"https://w3id.org/did-resolution\"');\n      expect(response.body.didDocumentMetadata.deactivated).to.eq(true);\n    });\n  });\n});",
              "err": {
                "message": "AssertionError: expected 404 to equal 410",
                "estack": "AssertionError: expected 404 to equal 410\n    at Context.eval (http://localhost:40051/__cypress/tests?p=cypress/integration/uniresolver_spec.js:232:40)",
                "diff": "- 404\n+ 410\n"
              },
              "uuid": "6228929f-9bc2-4f0e-9629-a2ff1875805c",
              "parentUUID": "9fcdf230-5016-47a3-8008-8c044f533da0",
              "isHook": false,
              "skipped": false
            }
          ],
          "suites": [],
          "passes": [],
          "failures": [
            "6228929f-9bc2-4f0e-9629-a2ff1875805c"
          ],
          "pending": [],
          "skipped": [],
          "duration": 72,
          "root": false,
          "rootEmpty": false,
          "_timeout": 2000
        },
        {
          "uuid": "097fb6a6-af9b-403e-94f1-34809086ab61",
          "title": "Test Scenario 5: Not found",
          "fullFile": "",
          "file": "",
          "beforeHooks": [],
          "afterHooks": [],
          "tests": [
            {
              "title": "Returns an HTTP code of 404 for non-existent DIDs",
              "fullTitle": "Test Scenario 5: Not found Returns an HTTP code of 404 for non-existent DIDs",
              "timedOut": null,
              "duration": 49,
              "state": "failed",
              "speed": null,
              "pass": false,
              "fail": true,
              "pending": false,
              "context": null,
              "code": "cy.fixture(path_example_dids).its(\"nonExisDids\").then(list => {\n  Object.keys(list).forEach(key => {\n    const nonExDid = list[key];\n    cy.request({\n      method: \"GET\",\n      url: endpoint + nonExDid,\n      failOnStatusCode: false\n    }).then(response => {\n      expect(response.status).to.eq(404);\n      expect(response.headers[\"content-type\"]).to.contain('application/ld+json;profile=\"https://w3id.org/did-resolution\"');\n      expect(response).to.be.a(\"object\");\n      expect(response.body.didResolutionMetadata.error).to.eq(\"notFound\");\n    });\n  });\n});",
              "err": {
                "message": "AssertionError: expected 501 to equal 404",
                "estack": "AssertionError: expected 501 to equal 404\n    at Context.eval (http://localhost:40051/__cypress/tests?p=cypress/integration/uniresolver_spec.js:254:40)",
                "diff": "- 501\n+ 404\n"
              },
              "uuid": "9ad0b98b-738e-43f0-bfc6-586b323746bd",
              "parentUUID": "097fb6a6-af9b-403e-94f1-34809086ab61",
              "isHook": false,
              "skipped": false
            }
          ],
          "suites": [],
          "passes": [],
          "failures": [
            "9ad0b98b-738e-43f0-bfc6-586b323746bd"
          ],
          "pending": [],
          "skipped": [],
          "duration": 49,
          "root": false,
          "rootEmpty": false,
          "_timeout": 2000
        },
        {
          "uuid": "0f7b686b-3157-43e2-a5c2-20a39f4186a9",
          "title": "Test Scenario 6A: Invalid DID",
          "fullFile": "",
          "file": "",
          "beforeHooks": [],
          "afterHooks": [],
          "tests": [
            {
              "title": "Returns a HTTP code of 400 for an invalid DID",
              "fullTitle": "Test Scenario 6A: Invalid DID Returns a HTTP code of 400 for an invalid DID",
              "timedOut": null,
              "duration": 67,
              "state": "passed",
              "speed": "fast",
              "pass": true,
              "fail": false,
              "pending": false,
              "context": null,
              "code": "cy.fixture(path_example_dids).its(\"invalidDids\").then(list => {\n  Object.keys(list).forEach(key => {\n    const invalidDid = list[key];\n    cy.request({\n      method: \"GET\",\n      url: endpoint + invalidDid,\n      failOnStatusCode: false\n    }).then(response => {\n      expect(response.status).to.eq(400);\n      expect(response.headers[\"content-type\"]).to.contain('application/ld+json;profile=\"https://w3id.org/did-resolution\"');\n      expect(response).to.be.a(\"object\");\n      expect(response.body.didResolutionMetadata.error).contains(\"invalidDid\");\n    });\n  });\n});",
              "err": {},
              "uuid": "a14f34e3-4515-464d-b2ac-7abf8b0a4e1a",
              "parentUUID": "0f7b686b-3157-43e2-a5c2-20a39f4186a9",
              "isHook": false,
              "skipped": false
            }
          ],
          "suites": [],
          "passes": [
            "a14f34e3-4515-464d-b2ac-7abf8b0a4e1a"
          ],
          "failures": [],
          "pending": [],
          "skipped": [],
          "duration": 67,
          "root": false,
          "rootEmpty": false,
          "_timeout": 2000
        },
        {
          "uuid": "790774f7-bd2d-4501-b46c-0e8a3bfda939",
          "title": "Test Scenario 6B: method not supported DIDs",
          "fullFile": "",
          "file": "",
          "beforeHooks": [],
          "afterHooks": [],
          "tests": [
            {
              "title": "Raises an error for unsupported DID methods",
              "fullTitle": "Test Scenario 6B: method not supported DIDs Raises an error for unsupported DID methods",
              "timedOut": null,
              "duration": 42,
              "state": "failed",
              "speed": null,
              "pass": false,
              "fail": true,
              "pending": false,
              "context": null,
              "code": "cy.fixture(path_example_dids).its(\"methodNotSupportedDids\").then(list => {\n  Object.keys(list).forEach(key => {\n    const invalidDid = list[key];\n    cy.request({\n      method: \"GET\",\n      url: endpoint + invalidDid,\n      failOnStatusCode: false\n    }).then(response => {\n      expect(response.body.didResolutionMetadata.error).contains(\"methodNotSupported\");\n      expect(response).to.be.a(\"object\"); // todo: should this be 404 or 400?\n      expect(response.status).to.eq(400); // returns 501\n      expect(response.headers[\"content-type\"]).to.contain('application/ld+json;profile=\"https://w3id.org/did-resolution\"');\n    });\n  });\n});",
              "err": {
                "message": "AssertionError: expected 501 to equal 400",
                "estack": "AssertionError: expected 501 to equal 400\n    at Context.eval (http://localhost:40051/__cypress/tests?p=cypress/integration/uniresolver_spec.js:301:40)",
                "diff": "- 501\n+ 400\n"
              },
              "uuid": "45437ad3-fab5-470a-baf7-e465bb4dd9ab",
              "parentUUID": "790774f7-bd2d-4501-b46c-0e8a3bfda939",
              "isHook": false,
              "skipped": false
            }
          ],
          "suites": [],
          "passes": [],
          "failures": [
            "45437ad3-fab5-470a-baf7-e465bb4dd9ab"
          ],
          "pending": [],
          "skipped": [],
          "duration": 42,
          "root": false,
          "rootEmpty": false,
          "_timeout": 2000
        },
        {
          "uuid": "ea3d629d-8b40-4ff0-8fbc-8f944ccf54e9",
          "title": "Test Scenario 6C: invalid verificationMethod.id",
          "fullFile": "",
          "file": "",
          "beforeHooks": [],
          "afterHooks": [],
          "tests": [
            {
              "title": "Raises error when verificationMethod.id is invalid",
              "fullTitle": "Test Scenario 6C: invalid verificationMethod.id Raises error when verificationMethod.id is invalid",
              "timedOut": null,
              "duration": 456,
              "state": "failed",
              "speed": null,
              "pass": false,
              "fail": true,
              "pending": false,
              "context": null,
              "code": "cy.fixture(path_example_dids).its(\"invalidVerificationMethodId\").then(list => {\n  Object.keys(list).forEach(key => {\n    const invalidDid = list[key];\n    cy.request({\n      method: \"GET\",\n      url: endpoint + invalidDid,\n      failOnStatusCode: false\n    }).then(response => {\n      expect(response).to.be.a(\"object\");\n      expect(response.headers[\"content-type\"]).to.contain('application/ld+json;profile=\"https://w3id.org/did-resolution\"'); // todo: should this be 404 or 400?\n      expect(response.status).to.eq(400); // return 200\n      expect(response.body.didResolutionMetadata.error).contains(\"invalidDidUrl\"); // doesn't exist\n    });\n  });\n});",
              "err": {
                "message": "AssertionError: expected 200 to equal 400",
                "estack": "AssertionError: expected 200 to equal 400\n    at Context.eval (http://localhost:40051/__cypress/tests?p=cypress/integration/uniresolver_spec.js:326:40)",
                "diff": "- 200\n+ 400\n"
              },
              "uuid": "f1938875-f3a3-4243-8317-c8046abb48c7",
              "parentUUID": "ea3d629d-8b40-4ff0-8fbc-8f944ccf54e9",
              "isHook": false,
              "skipped": false
            }
          ],
          "suites": [],
          "passes": [],
          "failures": [
            "f1938875-f3a3-4243-8317-c8046abb48c7"
          ],
          "pending": [],
          "skipped": [],
          "duration": 456,
          "root": false,
          "rootEmpty": false,
          "_timeout": 2000
        },
        {
          "uuid": "cda89a23-72c3-4542-9344-20fc3ea7be29",
          "title": "Test Scenario 6D: invalid verificationMethod.controller",
          "fullFile": "",
          "file": "",
          "beforeHooks": [],
          "afterHooks": [],
          "tests": [
            {
              "title": "Raises error when verificationMethod.controller is invalid",
              "fullTitle": "Test Scenario 6D: invalid verificationMethod.controller Raises error when verificationMethod.controller is invalid",
              "timedOut": null,
              "duration": 179,
              "state": "failed",
              "speed": null,
              "pass": false,
              "fail": true,
              "pending": false,
              "context": null,
              "code": "cy.fixture(path_example_dids).its(\"invalidVerificationMethodController\").then(list => {\n  Object.keys(list).forEach(key => {\n    const invalidDid = list[key];\n    cy.request({\n      method: \"GET\",\n      url: endpoint + invalidDid,\n      failOnStatusCode: false\n    }).then(response => {\n      expect(response).to.be.a(\"object\");\n      expect(response.headers[\"content-type\"]).to.contain('application/ld+json;profile=\"https://w3id.org/did-resolution\"'); // todo: should this be 404 or 400?\n      expect(response.status).to.eq(400); // returns 200\n      expect(response.body.didResolutionMetadata.error).contains(\"invalidDid\"); // doesn't exist\n    });\n  });\n});",
              "err": {
                "message": "AssertionError: expected 200 to equal 400",
                "estack": "AssertionError: expected 200 to equal 400\n    at Context.eval (http://localhost:40051/__cypress/tests?p=cypress/integration/uniresolver_spec.js:350:40)",
                "diff": "- 200\n+ 400\n"
              },
              "uuid": "a1c13f2b-54d2-4847-945f-0a7733fd1669",
              "parentUUID": "cda89a23-72c3-4542-9344-20fc3ea7be29",
              "isHook": false,
              "skipped": false
            }
          ],
          "suites": [],
          "passes": [],
          "failures": [
            "a1c13f2b-54d2-4847-945f-0a7733fd1669"
          ],
          "pending": [],
          "skipped": [],
          "duration": 179,
          "root": false,
          "rootEmpty": false,
          "_timeout": 2000
        },
        {
          "uuid": "8966910a-a79d-430c-b7dd-e6f3984acb65",
          "title": "Test Scenario 6E: invalid didDocument.id",
          "fullFile": "",
          "file": "",
          "beforeHooks": [],
          "afterHooks": [],
          "tests": [
            {
              "title": "Raises error when didDocument.id is invalid",
              "fullTitle": "Test Scenario 6E: invalid didDocument.id Raises error when didDocument.id is invalid",
              "timedOut": null,
              "duration": 29,
              "state": "passed",
              "speed": "fast",
              "pass": true,
              "fail": false,
              "pending": false,
              "context": null,
              "code": "cy.fixture(path_example_dids).its(\"invalidDidDocumentId\").then(list => {\n  Object.keys(list).forEach(key => {\n    const invalidDid = list[key];\n    cy.request({\n      method: \"GET\",\n      url: endpoint + invalidDid,\n      failOnStatusCode: false\n    }).then(response => {\n      expect(response).to.be.a(\"object\");\n      expect(response.headers[\"content-type\"]).to.contain('application/ld+json;profile=\"https://w3id.org/did-resolution\"');\n      expect(response.status).to.eq(400);\n      expect(response.body.didResolutionMetadata.error).contains(\"invalidDid\");\n    });\n  });\n});",
              "err": {},
              "uuid": "548c2968-bee4-4240-93c4-d096c14592b2",
              "parentUUID": "8966910a-a79d-430c-b7dd-e6f3984acb65",
              "isHook": false,
              "skipped": false
            }
          ],
          "suites": [],
          "passes": [
            "548c2968-bee4-4240-93c4-d096c14592b2"
          ],
          "failures": [],
          "pending": [],
          "skipped": [],
          "duration": 29,
          "root": false,
          "rootEmpty": false,
          "_timeout": 2000
        },
        {
          "uuid": "112eb6b0-88ef-4237-ac87-b39fa4dce3b9",
          "title": "Test Scenario 6F: Invalid didDocument scheme",
          "fullFile": "",
          "file": "",
          "beforeHooks": [],
          "afterHooks": [],
          "tests": [
            {
              "title": "Raises invalidDid error when if scheme is not did",
              "fullTitle": "Test Scenario 6F: Invalid didDocument scheme Raises invalidDid error when if scheme is not did",
              "timedOut": null,
              "duration": 32,
              "state": "passed",
              "speed": "fast",
              "pass": true,
              "fail": false,
              "pending": false,
              "context": null,
              "code": "cy.fixture(path_example_dids).its(\"invalidDidScheme\").then(list => {\n  Object.keys(list).forEach(key => {\n    const invalidDid = list[key];\n    cy.request({\n      method: \"GET\",\n      url: endpoint + invalidDid,\n      failOnStatusCode: false\n    }).then(response => {\n      expect(response).to.be.a(\"object\");\n      expect(response.headers[\"content-type\"]).to.contain('application/ld+json;profile=\"https://w3id.org/did-resolution\"');\n      expect(response.status).to.eq(400);\n      expect(response.body.didResolutionMetadata.error).contains(\"invalidDid\");\n    });\n  });\n});",
              "err": {},
              "uuid": "4ef1d023-bef7-40d7-905e-53d3cda10713",
              "parentUUID": "112eb6b0-88ef-4237-ac87-b39fa4dce3b9",
              "isHook": false,
              "skipped": false
            }
          ],
          "suites": [],
          "passes": [
            "4ef1d023-bef7-40d7-905e-53d3cda10713"
          ],
          "failures": [],
          "pending": [],
          "skipped": [],
          "duration": 32,
          "root": false,
          "rootEmpty": false,
          "_timeout": 2000
        },
        {
          "uuid": "b1a5b2d8-99a2-4895-a563-0031111f6c0a",
          "title": "Test Scenario 6G: notAllowedLocalDerivedKey error/warning",
          "fullFile": "",
          "file": "",
          "beforeHooks": [],
          "afterHooks": [],
          "tests": [
            {
              "title": "Raises notAllowedLocalDerivedKey error when did is incorrect",
              "fullTitle": "Test Scenario 6G: notAllowedLocalDerivedKey error/warning Raises notAllowedLocalDerivedKey error when did is incorrect",
              "timedOut": null,
              "duration": 554,
              "state": "failed",
              "speed": null,
              "pass": false,
              "fail": true,
              "pending": false,
              "context": null,
              "code": "cy.fixture(path_example_dids).its(\"notAllowedLocalDerivedKey\").then(list => {\n  Object.keys(list).forEach(key => {\n    const invalidDid = list[key];\n    cy.request({\n      method: \"GET\",\n      url: endpoint + invalidDid,\n      failOnStatusCode: false\n    }).then(response => {\n      expect(response).to.be.a(\"object\");\n      expect(response.headers[\"content-type\"]).to.contain('application/ld+json;profile=\"https://w3id.org/did-resolution\"');\n      expect(response.status).to.eq(400);\n      expect(response.body.didResolutionMetadata.error).contains(\"notAllowedLocalDerivedKey\");\n    });\n  });\n});",
              "err": {
                "message": "AssertionError: expected 200 to equal 400",
                "estack": "AssertionError: expected 200 to equal 400\n    at Context.eval (http://localhost:40051/__cypress/tests?p=cypress/integration/uniresolver_spec.js:417:40)",
                "diff": "- 200\n+ 400\n"
              },
              "uuid": "7a419133-f710-4b91-b2a0-79cb6ffc46ad",
              "parentUUID": "b1a5b2d8-99a2-4895-a563-0031111f6c0a",
              "isHook": false,
              "skipped": false
            }
          ],
          "suites": [],
          "passes": [],
          "failures": [
            "7a419133-f710-4b91-b2a0-79cb6ffc46ad"
          ],
          "pending": [],
          "skipped": [],
          "duration": 554,
          "root": false,
          "rootEmpty": false,
          "_timeout": 2000
        },
        {
          "uuid": "5711dca8-767e-4b5d-99f9-9799434d5f2c",
          "title": "Test Scenario 6H: notAllowedLocalDuplicateKey error/warning",
          "fullFile": "",
          "file": "",
          "beforeHooks": [],
          "afterHooks": [],
          "tests": [
            {
              "title": "Raises notAllowedLocalDuplicateKey error when did is incorrect",
              "fullTitle": "Test Scenario 6H: notAllowedLocalDuplicateKey error/warning Raises notAllowedLocalDuplicateKey error when did is incorrect",
              "timedOut": null,
              "duration": 52,
              "state": "failed",
              "speed": null,
              "pass": false,
              "fail": true,
              "pending": false,
              "context": null,
              "code": "cy.fixture(path_example_dids).its(\"invalidDidDocumentId\").then(list => {\n  Object.keys(list).forEach(key => {\n    const invalidDid = list[key];\n    cy.request({\n      method: \"GET\",\n      url: endpoint + invalidDid,\n      failOnStatusCode: false\n    }).then(response => {\n      expect(response).to.be.a(\"object\");\n      expect(response.headers[\"content-type\"]).to.contain('application/ld+json;profile=\"https://w3id.org/did-resolution\"');\n      expect(response.status).to.eq(400);\n      expect(response.body.didResolutionMetadata.error).contains(\"notAllowedLocalDuplicateKey\");\n    });\n  });\n});",
              "err": {
                "message": "AssertionError: expected 'invalidDid' to include 'notAllowedLocalDuplicateKey'",
                "estack": "AssertionError: expected 'invalidDid' to include 'notAllowedLocalDuplicateKey'\n    at Context.eval (http://localhost:40051/__cypress/tests?p=cypress/integration/uniresolver_spec.js:440:63)",
                "diff": null
              },
              "uuid": "22bc71b4-a330-4ea9-85de-ac892c665f68",
              "parentUUID": "5711dca8-767e-4b5d-99f9-9799434d5f2c",
              "isHook": false,
              "skipped": false
            }
          ],
          "suites": [],
          "passes": [],
          "failures": [
            "22bc71b4-a330-4ea9-85de-ac892c665f68"
          ],
          "pending": [],
          "skipped": [],
          "duration": 52,
          "root": false,
          "rootEmpty": false,
          "_timeout": 2000
        },
        {
          "uuid": "d4b4c52b-7db9-4775-8e74-4c110cb9522e",
          "title": "Test Scenario 6I: notAllowedKeyType error/warning",
          "fullFile": "",
          "file": "",
          "beforeHooks": [],
          "afterHooks": [],
          "tests": [
            {
              "title": "Raises notAllowedKeyType error when did is incorrect",
              "fullTitle": "Test Scenario 6I: notAllowedKeyType error/warning Raises notAllowedKeyType error when did is incorrect",
              "timedOut": null,
              "duration": 51,
              "state": "failed",
              "speed": null,
              "pass": false,
              "fail": true,
              "pending": false,
              "context": null,
              "code": "cy.fixture(path_example_dids).its(\"invalidDidDocumentId\").then(list => {\n  Object.keys(list).forEach(key => {\n    const invalidDid = list[key];\n    cy.request({\n      method: \"GET\",\n      url: endpoint + invalidDid,\n      failOnStatusCode: false\n    }).then(response => {\n      expect(response).to.be.a(\"object\");\n      expect(response.headers[\"content-type\"]).to.contain('application/ld+json;profile=\"https://w3id.org/did-resolution\"');\n      expect(response.status).to.eq(400);\n      expect(response.body.didResolutionMetadata.error).contains(\"notAllowedKeyType\");\n    });\n  });\n});",
              "err": {
                "message": "AssertionError: expected 'invalidDid' to include 'notAllowedKeyType'",
                "estack": "AssertionError: expected 'invalidDid' to include 'notAllowedKeyType'\n    at Context.eval (http://localhost:40051/__cypress/tests?p=cypress/integration/uniresolver_spec.js:462:63)",
                "diff": null
              },
              "uuid": "47247c35-08fa-4f49-8cc5-da956cc62ced",
              "parentUUID": "d4b4c52b-7db9-4775-8e74-4c110cb9522e",
              "isHook": false,
              "skipped": false
            }
          ],
          "suites": [],
          "passes": [],
          "failures": [
            "47247c35-08fa-4f49-8cc5-da956cc62ced"
          ],
          "pending": [],
          "skipped": [],
          "duration": 51,
          "root": false,
          "rootEmpty": false,
          "_timeout": 2000
        },
        {
          "uuid": "52953134-14a4-48d5-9ec2-b430a8c321c0",
          "title": "Test Scenario 6J: notAllowedMethod error/warning",
          "fullFile": "",
          "file": "",
          "beforeHooks": [],
          "afterHooks": [],
          "tests": [
            {
              "title": "Raises notAllowedMethod error when did is incorrect",
              "fullTitle": "Test Scenario 6J: notAllowedMethod error/warning Raises notAllowedMethod error when did is incorrect",
              "timedOut": null,
              "duration": 77,
              "state": "failed",
              "speed": null,
              "pass": false,
              "fail": true,
              "pending": false,
              "context": null,
              "code": "cy.fixture(path_example_dids).its(\"notAllowedMethod\").then(list => {\n  Object.keys(list).forEach(key => {\n    const invalidDid = list[key];\n    cy.request({\n      method: \"GET\",\n      url: endpoint + invalidDid,\n      failOnStatusCode: false\n    }).then(response => {\n      expect(response).to.be.a(\"object\");\n      expect(response.headers[\"content-type\"]).to.contain('application/ld+json;profile=\"https://w3id.org/did-resolution\"');\n      expect(response.status).to.eq(400);\n      expect(response.body.didResolutionMetadata.error).contains(\"notAllowedMethod\");\n    });\n  });\n});",
              "err": {
                "message": "AssertionError: expected 404 to equal 400",
                "estack": "AssertionError: expected 404 to equal 400\n    at Context.eval (http://localhost:40051/__cypress/tests?p=cypress/integration/uniresolver_spec.js:484:40)",
                "diff": "- 404\n+ 400\n"
              },
              "uuid": "44723722-3fb5-4022-a7a5-a4ae11129dec",
              "parentUUID": "52953134-14a4-48d5-9ec2-b430a8c321c0",
              "isHook": false,
              "skipped": false
            }
          ],
          "suites": [],
          "passes": [],
          "failures": [
            "44723722-3fb5-4022-a7a5-a4ae11129dec"
          ],
          "pending": [],
          "skipped": [],
          "duration": 77,
          "root": false,
          "rootEmpty": false,
          "_timeout": 2000
        },
        {
          "uuid": "d72fdc76-897e-4896-a136-e73275dea6d3",
          "title": "Test Scenario 7: DID URLs with fragments",
          "fullFile": "",
          "file": "",
          "beforeHooks": [],
          "afterHooks": [],
          "tests": [
            {
              "title": "Can resolve a DID with a fragment",
              "fullTitle": "Test Scenario 7: DID URLs with fragments Can resolve a DID with a fragment",
              "timedOut": null,
              "duration": 52,
              "state": "failed",
              "speed": null,
              "pass": false,
              "fail": true,
              "pending": false,
              "context": null,
              "code": "cy.fixture(path_example_dids).its(\"fragmentDids\").then(list => {\n  Object.keys(list).forEach(key => {\n    const fragmentDid = list[key];\n    cy.request({\n      method: \"GET\",\n      url: endpoint + fragmentDid,\n      failOnStatusCode: false,\n      headers: {\n        Accept: \"application/did+ld+json\",\n        Authorization: \"Bearer b082c420-df67-4b06-899c-b7c51d75fba0\"\n      }\n    }).as(\"request\");\n    cy.get(\"@request\").then(response => {\n      expect(response.status).to.eq(200);\n      expect(response.headers[\"content-type\"]).to.contain(\"application/did+ld+json\");\n      expect(response.body).not.to.have.property(\"didDocument\");\n      expect(response.body).to.have.property(\"id\");\n      expect(response.body[\"id\"]).to.contain(decodeURIComponent(fragmentDid.split(\"#\")[0]));\n    });\n  });\n});",
              "err": {
                "message": "AssertionError: expected 400 to equal 200",
                "estack": "AssertionError: expected 400 to equal 200\n    at Context.eval (http://localhost:40051/__cypress/tests?p=cypress/integration/uniresolver_spec.js:509:40)",
                "diff": "- 400\n+ 200\n"
              },
              "uuid": "a0a973b1-4d5d-4aa2-a19f-a99bf8d07357",
              "parentUUID": "d72fdc76-897e-4896-a136-e73275dea6d3",
              "isHook": false,
              "skipped": false
            }
          ],
          "suites": [],
          "passes": [],
          "failures": [
            "a0a973b1-4d5d-4aa2-a19f-a99bf8d07357"
          ],
          "pending": [],
          "skipped": [],
          "duration": 52,
          "root": false,
          "rootEmpty": false,
          "_timeout": 2000
        },
        {
          "uuid": "5510a371-e2c9-47e6-84ec-d51a2b3c8d3f",
          "title": "Test Scenario 8: Service and relativeRef parameters",
          "fullFile": "",
          "file": "",
          "beforeHooks": [],
          "afterHooks": [],
          "tests": [
            {
              "title": "Fetches DID",
              "fullTitle": "Test Scenario 8: Service and relativeRef parameters Fetches DID",
              "timedOut": null,
              "duration": 78,
              "state": "passed",
              "speed": "fast",
              "pass": true,
              "fail": false,
              "pending": false,
              "context": null,
              "code": "cy.fixture(path_example_dids).its(\"relativeParamDids\").then(list => {\n  Object.keys(list).forEach(key => {\n    const fragmentDid = list[key];\n    console.log(\"FRAGMENT DID IS\", fragmentDid);\n    cy.request({\n      method: \"GET\",\n      url: endpoint + fragmentDid,\n      headers: {\n        Accept: \"text/uri-list\"\n      },\n      failOnStatusCode: false\n    }).as(\"response\");\n    it(\"MUST return HTTP response status equals 303\", () => {\n      cy.get(\"@response\").then(response => {\n        expect(response.status).to.eq(303);\n      });\n    });\n  });\n});",
              "err": {},
              "uuid": "2672b897-0ed5-48ed-af19-e2b08d1ed3c8",
              "parentUUID": "5510a371-e2c9-47e6-84ec-d51a2b3c8d3f",
              "isHook": false,
              "skipped": false
            }
          ],
          "suites": [],
          "passes": [
            "2672b897-0ed5-48ed-af19-e2b08d1ed3c8"
          ],
          "failures": [],
          "pending": [],
          "skipped": [],
          "duration": 78,
          "root": false,
          "rootEmpty": false,
          "_timeout": 2000
        },
        {
          "uuid": "7cbfbe3e-b063-498b-a99c-fdfa82d30f7a",
          "title": "Test Scenario 9: DID URLs with transformKeys",
          "fullFile": "",
          "file": "",
          "beforeHooks": [],
          "afterHooks": [],
          "tests": [
            {
              "title": "MUST return HTTP response status 200",
              "fullTitle": "Test Scenario 9: DID URLs with transformKeys MUST return HTTP response status 200",
              "timedOut": null,
              "duration": 49,
              "state": "failed",
              "speed": null,
              "pass": false,
              "fail": true,
              "pending": false,
              "context": null,
              "code": "cy.fixture(path_example_dids).its(\"transformKeyDids\").then(list => {\n  Object.keys(list).forEach(key => {\n    const transformKeyDid = list[key];\n    cy.request({\n      method: \"GET\",\n      url: endpoint + transformKeyDid,\n      headers: {\n        Accept: \"application/did+ld+json\",\n        Authorization: \"Bearer b082c420-df67-4b06-899c-b7c51d75fba0\"\n      },\n      failOnStatusCode: false\n    }).as(\"request\");\n    cy.get(\"@request\").then(response => {\n      expect(response.status).to.eq(200);\n      expect(response).to.be.a(\"object\");\n      response.body.verificationMethod.forEach(out => {\n        expect(out).has.property(\"type\").to.be.oneOf([\"JsonWebKey2020\", \"Ed25519VerificationKey2018\", \"X25519KeyAgreementKey2019\"]);\n      });\n      expect(response.headers[\"content-type\"]).contains(\"application/did+ld+json\");\n      expect(response.body).has.property(\"id\", decodeURIComponent(transformKeyDid.split(\"?\")[0].split(\"#\")[0]));\n    });\n  });\n});",
              "err": {
                "message": "AssertionError: expected 400 to equal 200",
                "estack": "AssertionError: expected 400 to equal 200\n    at Context.eval (http://localhost:40051/__cypress/tests?p=cypress/integration/uniresolver_spec.js:564:40)",
                "diff": "- 400\n+ 200\n"
              },
              "uuid": "dc06d5f2-b99a-46b0-986b-65354fbe6753",
              "parentUUID": "7cbfbe3e-b063-498b-a99c-fdfa82d30f7a",
              "isHook": false,
              "skipped": false
            }
          ],
          "suites": [],
          "passes": [],
          "failures": [
            "dc06d5f2-b99a-46b0-986b-65354fbe6753"
          ],
          "pending": [],
          "skipped": [],
          "duration": 49,
          "root": false,
          "rootEmpty": false,
          "_timeout": 2000
        },
        {
          "uuid": "c0ae90f9-209d-4aba-a3de-9438ab15ea5c",
          "title": "Test Scenario 10: DID URLs with versionTime parameter",
          "fullFile": "",
          "file": "",
          "beforeHooks": [],
          "afterHooks": [],
          "tests": [
            {
              "title": "MUST return HTTP response status 200",
              "fullTitle": "Test Scenario 10: DID URLs with versionTime parameter MUST return HTTP response status 200",
              "timedOut": null,
              "duration": 82,
              "state": "failed",
              "speed": null,
              "pass": false,
              "fail": true,
              "pending": false,
              "context": null,
              "code": "cy.fixture(path_example_dids).its(\"versionTimeDids\").then(list => {\n  Object.keys(list).forEach(key => {\n    const versionTimeDid = list[key];\n    cy.request({\n      method: \"GET\",\n      url: endpoint + versionTimeDid,\n      headers: {\n        Accept: \"application/did+ld+json\",\n        Authorization: \"Bearer b082c420-df67-4b06-899c-b7c51d75fba0\"\n      },\n      failOnStatusCode: false\n    }).as(\"request\");\n    cy.get(\"@request\").then(response => {\n      expect(response.status).to.eq(200);\n      expect(response.headers[\"content-type\"]).contains(\"application/did+ld+json\");\n      expect(response).to.be.a(\"object\");\n      expect(response.body).has.property(\"id\").contains(\"did:sov:DjxRxnL4gXsncbH8jM8ySM\");\n    });\n  });\n});",
              "err": {
                "message": "AssertionError: expected 400 to equal 200",
                "estack": "AssertionError: expected 400 to equal 200\n    at Context.eval (http://localhost:40051/__cypress/tests?p=cypress/integration/uniresolver_spec.js:594:40)",
                "diff": "- 400\n+ 200\n"
              },
              "uuid": "6c5b385c-ff98-4bac-9ec7-851b62a3858b",
              "parentUUID": "c0ae90f9-209d-4aba-a3de-9438ab15ea5c",
              "isHook": false,
              "skipped": false
            }
          ],
          "suites": [],
          "passes": [],
          "failures": [
            "6c5b385c-ff98-4bac-9ec7-851b62a3858b"
          ],
          "pending": [],
          "skipped": [],
          "duration": 82,
          "root": false,
          "rootEmpty": false,
          "_timeout": 2000
        },
        {
          "uuid": "ac581889-0eeb-4eb7-aa1c-e85a6b5aec40",
          "title": "Test Scenario 11: DID URLs with versionId parameter",
          "fullFile": "",
          "file": "",
          "beforeHooks": [],
          "afterHooks": [],
          "tests": [
            {
              "title": "MUST return HTTP response status 200",
              "fullTitle": "Test Scenario 11: DID URLs with versionId parameter MUST return HTTP response status 200",
              "timedOut": null,
              "duration": 55,
              "state": "failed",
              "speed": null,
              "pass": false,
              "fail": true,
              "pending": false,
              "context": null,
              "code": "cy.fixture(path_example_dids).its(\"versionIdDids\").then(list => {\n  Object.keys(list).forEach(key => {\n    const versionIdDid = list[key];\n    cy.request({\n      method: \"GET\",\n      url: endpoint + versionIdDid,\n      headers: {\n        Accept: \"application/did+ld+json\",\n        Authorization: \"Bearer b082c420-df67-4b06-899c-b7c51d75fba0\"\n      },\n      failOnStatusCode: false\n    }).as(\"request\");\n    cy.get(\"@request\").then(response => {\n      expect(response.status).to.eq(200);\n      expect(response).to.be.a(\"object\");\n      expect(response.headers[\"content-type\"]).contains(\"application/did+ld+json\");\n      expect(response.body).has.property(\"id\").contains(decodeURIComponent(versionIdDid.split(\"?\")[0]));\n    });\n  });\n});",
              "err": {
                "message": "AssertionError: expected 400 to equal 200",
                "estack": "AssertionError: expected 400 to equal 200\n    at Context.eval (http://localhost:40051/__cypress/tests?p=cypress/integration/uniresolver_spec.js:621:40)",
                "diff": "- 400\n+ 200\n"
              },
              "uuid": "837d1a50-29a1-473a-a0b5-cd98f9aad41b",
              "parentUUID": "ac581889-0eeb-4eb7-aa1c-e85a6b5aec40",
              "isHook": false,
              "skipped": false
            }
          ],
          "suites": [],
          "passes": [],
          "failures": [
            "837d1a50-29a1-473a-a0b5-cd98f9aad41b"
          ],
          "pending": [],
          "skipped": [],
          "duration": 55,
          "root": false,
          "rootEmpty": false,
          "_timeout": 2000
        },
        {
          "uuid": "f8bc522c-3ea8-4889-8d4a-61f6a00ea6e3",
          "title": "Test Scenario 12: Resolve a DID / dereference a DID URL",
          "fullFile": "",
          "file": "",
          "beforeHooks": [],
          "afterHooks": [],
          "tests": [
            {
              "title": "MUST return HTTP response status 200",
              "fullTitle": "Test Scenario 12: Resolve a DID / dereference a DID URL MUST return HTTP response status 200",
              "timedOut": null,
              "duration": 88,
              "state": "failed",
              "speed": null,
              "pass": false,
              "fail": true,
              "pending": false,
              "context": null,
              "code": "cy.fixture(path_example_dids).its(\"normalDids\").then(list => {\n  Object.keys(list).forEach(key => {\n    const normalDid = list[key];\n    cy.request({\n      method: \"GET\",\n      url: endpoint + normalDid,\n      headers: {\n        Accept: \"application/json\"\n      },\n      failOnStatusCode: false\n    }).as(\"request\");\n    cy.get(\"@request\").then(response => {\n      console.log(\"normal did is:\", normalDid);\n      expect(response.status).to.eq(200);\n      expect(response.headers[\"content-type\"]).contains(\"application/did+json;charset=utf-8\");\n      expect(response.body).has.property(\"id\", normalDid); // expect(response.body[\"keyAgreement\"][0]).to.contain(normalDid);\n    });\n  });\n});",
              "err": {
                "message": "AssertionError: expected 404 to equal 200",
                "estack": "AssertionError: expected 404 to equal 200\n    at Context.eval (http://localhost:40051/__cypress/tests?p=cypress/integration/uniresolver_spec.js:648:40)",
                "diff": "- 404\n+ 200\n"
              },
              "uuid": "20ad7d66-5332-47e1-8d8d-ea1820eb67b1",
              "parentUUID": "f8bc522c-3ea8-4889-8d4a-61f6a00ea6e3",
              "isHook": false,
              "skipped": false
            }
          ],
          "suites": [],
          "passes": [],
          "failures": [
            "20ad7d66-5332-47e1-8d8d-ea1820eb67b1"
          ],
          "pending": [],
          "skipped": [],
          "duration": 88,
          "root": false,
          "rootEmpty": false,
          "_timeout": 2000
        },
        {
          "uuid": "48ba363b-2941-4a68-a26b-f78ac8458db2",
          "title": "Test Scenario 12B: Resolve a DID / dereference a DID URL",
          "fullFile": "",
          "file": "",
          "beforeHooks": [],
          "afterHooks": [],
          "tests": [
            {
              "title": "MUST return HTTP response status 200",
              "fullTitle": "Test Scenario 12B: Resolve a DID / dereference a DID URL MUST return HTTP response status 200",
              "timedOut": null,
              "duration": 87,
              "state": "failed",
              "speed": null,
              "pass": false,
              "fail": true,
              "pending": false,
              "context": null,
              "code": "cy.fixture(path_example_dids).its(\"normalDids\").then(list => {\n  Object.keys(list).forEach(key => {\n    const normalDid = list[key];\n    cy.request({\n      method: \"GET\",\n      url: endpoint + normalDid,\n      headers: {\n        Accept: 'application/ld+json;profile=\"https://w3c-ccg.github.io/did-resolution/\"'\n      },\n      failOnStatusCode: false\n    }).as(\"request\");\n    cy.get(\"@request\").then(response => {\n      console.log(\"normal did is:\", normalDid);\n      expect(response.status).to.eq(200);\n      expect(response.headers[\"content-type\"]).contains('application/ld+json; profile=\"https://w3c-ccg.github.io/did-resolution/\"');\n    });\n  });\n});",
              "err": {
                "message": "AssertionError: expected 406 to equal 200",
                "estack": "AssertionError: expected 406 to equal 200\n    at Context.eval (http://localhost:40051/__cypress/tests?p=cypress/integration/uniresolver_spec.js:675:40)",
                "diff": "- 406\n+ 200\n"
              },
              "uuid": "eef4b1f9-a94c-44ec-a6df-ccf5a0849276",
              "parentUUID": "48ba363b-2941-4a68-a26b-f78ac8458db2",
              "isHook": false,
              "skipped": false
            }
          ],
          "suites": [],
          "passes": [],
          "failures": [
            "eef4b1f9-a94c-44ec-a6df-ccf5a0849276"
          ],
          "pending": [],
          "skipped": [],
          "duration": 87,
          "root": false,
          "rootEmpty": false,
          "_timeout": 2000
        }
      ],
      "passes": [],
      "failures": [],
      "pending": [],
      "skipped": [],
      "duration": 0,
      "root": true,
      "rootEmpty": true,
      "_timeout": 2000
    }
  ],
  "meta": {
    "mocha": {
      "version": "7.0.1"
    },
    "mochawesome": {
      "options": {
        "quiet": false,
        "reportFilename": "mochawesome",
        "saveHtml": false,
        "saveJson": true,
        "consoleReporter": "spec",
        "useInlineDiffs": false,
        "code": true
      },
      "version": "7.1.2"
    },
    "marge": {
      "options": {
        "reportDir": "reports/mocha",
        "configFile": "reporterOpts.json",
        "overwrite": false,
        "html": false,
        "json": true
      },
      "version": "6.1.1"
    }
  }
}