{
  "stats": {
    "suites": 1,
    "tests": 22,
    "passes": 4,
    "pending": 0,
    "failures": 18,
    "start": "2024-03-22T00:28:00.625Z",
    "end": "2024-03-22T00:28:04.877Z",
    "duration": 3892,
    "testsRegistered": 22,
    "passPercent": 18.181818181818183,
    "pendingPercent": 0,
    "other": 0,
    "hasOther": false,
    "skipped": 0,
    "hasSkipped": false
  },
  "results": [
    {
      "uuid": "507fbf1d-f021-4436-aeee-9e30ce6e9bf0",
      "title": "",
      "fullFile": "cypress/integration/uniresolver_spec.js",
      "file": "cypress/integration/uniresolver_spec.js",
      "beforeHooks": [],
      "afterHooks": [],
      "tests": [],
      "suites": [
        {
          "uuid": "cfe520ae-65aa-46dc-a67b-5c835ef89043",
          "title": "Test Scenario 1: DID Resolution Result fixtures: https://dev.uniresolver.io/1.0/identifiers/",
          "fullFile": "",
          "file": "",
          "beforeHooks": [],
          "afterHooks": [],
          "tests": [
            {
              "title": "A correct DID can be resolved",
              "fullTitle": "Test Scenario 1: DID Resolution Result fixtures: https://dev.uniresolver.io/1.0/identifiers/ A correct DID can be resolved",
              "timedOut": null,
              "duration": 605,
              "state": "failed",
              "speed": null,
              "pass": false,
              "fail": true,
              "pending": false,
              "context": null,
              "code": "cy.clearCookies();\ncy.fixture(path_example_dids).its(\"normalDids\").then(list => {\n  Object.keys(list).forEach(key => {\n    const normalDid = list[key];\n    cy.request({\n      method: \"GET\",\n      url: endpoint + normalDid,\n      failOnStatusCode: false\n    }).as(\"request\");\n    cy.get(\"@request\").then(response => {\n      expect(response.status).to.eq(200);\n    });\n    cy.get(\"@request\").then(response => {\n      expect(response.headers[\"content-type\"].replace(/\\s+/g, \"\")).contains('application/ld+json;profile=\"https://w3id.org/did-resolution');\n    });\n    cy.get(\"@request\").then(response => {\n      expect(response).to.be.a(\"object\");\n    });\n    cy.get(\"@request\").then(response => {\n      expect(response.body).to.have.property(\"didDocument\");\n    });\n    cy.get(\"@request\").then(response => {\n      expect(response.body).to.have.property(\"didResolutionMetadata\");\n    });\n    cy.get(\"@request\").then(response => {\n      expect(response.body).to.have.property(\"didDocumentMetadata\");\n    });\n    cy.get(\"@request\").then(response => {\n      expect(response.body.didDocument.id).to.be.a(\"string\").and.satisfy(msg => msg.startsWith(\"did:\"));\n    });\n  });\n});",
              "err": {
                "message": "AssertionError: expected 404 to equal 200",
                "estack": "AssertionError: expected 404 to equal 200\n    at Context.eval (http://localhost:38053/__cypress/tests?p=cypress/integration/uniresolver_spec.js:116:40)",
                "diff": "- 404\n+ 200\n"
              },
              "uuid": "52026697-fb19-4263-bd29-4a28dfc56414",
              "parentUUID": "cfe520ae-65aa-46dc-a67b-5c835ef89043",
              "isHook": false,
              "skipped": false
            }
          ],
          "suites": [],
          "passes": [],
          "failures": [
            "52026697-fb19-4263-bd29-4a28dfc56414"
          ],
          "pending": [],
          "skipped": [],
          "duration": 605,
          "root": false,
          "rootEmpty": false,
          "_timeout": 2000
        },
        {
          "uuid": "23540073-3ae8-4e7e-9f81-3764d583ca3b",
          "title": "Test Scenario 2: JSON-LD DID document",
          "fullFile": "",
          "file": "",
          "beforeHooks": [],
          "afterHooks": [],
          "tests": [
            {
              "title": "A correct DID can be resolved with header input",
              "fullTitle": "Test Scenario 2: JSON-LD DID document A correct DID can be resolved with header input",
              "timedOut": null,
              "duration": 139,
              "state": "failed",
              "speed": null,
              "pass": false,
              "fail": true,
              "pending": false,
              "context": null,
              "code": "cy.fixture(path_example_dids).its(\"normalDids\").then(list => {\n  Object.keys(list).forEach(key => {\n    const normalDid = list[key];\n    cy.request({\n      method: \"GET\",\n      url: endpoint + normalDid,\n      headers: {\n        Accept: \"application/did+ld+json\"\n      },\n      failOnStatusCode: false\n    }).as(\"request\");\n    cy.get(\"@request\").then(response => {\n      expect(response.status).to.eq(200);\n      expect(response.headers[\"content-type\"]).to.contain(\"application/did+ld+json\");\n      cy.get(\"@request\").then(response => {\n        expect(response).to.be.a(\"object\");\n      });\n      expect(response.body).not.to.have.property(\"didDocument\");\n      expect(response.body[\"id\"]).to.contain(normalDid);\n    });\n  });\n});",
              "err": {
                "message": "AssertionError: expected 404 to equal 200",
                "estack": "AssertionError: expected 404 to equal 200\n    at Context.eval (http://localhost:38053/__cypress/tests?p=cypress/integration/uniresolver_spec.js:157:40)",
                "diff": "- 404\n+ 200\n"
              },
              "uuid": "daedb952-4e05-41a1-b8cf-a10b996d2016",
              "parentUUID": "23540073-3ae8-4e7e-9f81-3764d583ca3b",
              "isHook": false,
              "skipped": false
            }
          ],
          "suites": [],
          "passes": [],
          "failures": [
            "daedb952-4e05-41a1-b8cf-a10b996d2016"
          ],
          "pending": [],
          "skipped": [],
          "duration": 139,
          "root": false,
          "rootEmpty": false,
          "_timeout": 2000
        },
        {
          "uuid": "cd827585-bd97-4dfb-8316-4bd15a85046b",
          "title": "Test Scenario 3: Representation not supported",
          "fullFile": "",
          "file": "",
          "beforeHooks": [],
          "afterHooks": [],
          "tests": [
            {
              "title": "Shows an error when a representation is prompted",
              "fullTitle": "Test Scenario 3: Representation not supported Shows an error when a representation is prompted",
              "timedOut": null,
              "duration": 153,
              "state": "failed",
              "speed": null,
              "pass": false,
              "fail": true,
              "pending": false,
              "context": null,
              "code": "cy.fixture(path_example_dids).its(\"normalDids\").then(list => {\n  Object.keys(list).forEach(key => {\n    const normalDid = list[key];\n    cy.request({\n      method: \"GET\",\n      url: endpoint + normalDid,\n      headers: {\n        Accept: \"image/png\"\n      },\n      failOnStatusCode: false\n    }).then(response => {\n      expect(response.status).to.eq(406);\n      console.log(response);\n      expect(response.body.dereferencingMetadata.error).to.eq('\"representationNotSupported\"');\n    });\n  });\n});",
              "err": {
                "message": "TypeError: Cannot read properties of undefined (reading 'error')",
                "estack": "TypeError: Cannot read properties of undefined (reading 'error')\n    at Context.eval (http://localhost:38053/__cypress/tests?p=cypress/integration/uniresolver_spec.js:213:56)",
                "diff": null
              },
              "uuid": "9e857801-6a95-4cb0-9ad0-cdbb13b984e0",
              "parentUUID": "cd827585-bd97-4dfb-8316-4bd15a85046b",
              "isHook": false,
              "skipped": false
            }
          ],
          "suites": [],
          "passes": [],
          "failures": [
            "9e857801-6a95-4cb0-9ad0-cdbb13b984e0"
          ],
          "pending": [],
          "skipped": [],
          "duration": 153,
          "root": false,
          "rootEmpty": false,
          "_timeout": 2000
        },
        {
          "uuid": "04bc34cd-a165-4f7a-a895-c74643204ea3",
          "title": "Test Scenario 4: Deactivated",
          "fullFile": "",
          "file": "",
          "beforeHooks": [],
          "afterHooks": [],
          "tests": [
            {
              "title": "Returns an HTTP code of 410 for deactivated DIDs",
              "fullTitle": "Test Scenario 4: Deactivated Returns an HTTP code of 410 for deactivated DIDs",
              "timedOut": null,
              "duration": 81,
              "state": "failed",
              "speed": null,
              "pass": false,
              "fail": true,
              "pending": false,
              "context": null,
              "code": "cy.fixture(path_example_dids).its(\"deacDids\").then(list => {\n  Object.keys(list).forEach(key => {\n    const deacDid = list[key];\n    cy.request({\n      method: \"GET\",\n      url: endpoint + deacDid,\n      failOnStatusCode: false\n    }).then(response => {\n      expect(response.status).to.eq(410);\n      expect(response).to.be.a(\"object\");\n      expect(response.headers[\"content-type\"]).to.contain('application/ld+json;profile=\"https://w3id.org/did-resolution\"');\n      expect(response.body.didDocumentMetadata.deactivated).to.eq(true);\n    });\n  });\n});",
              "err": {
                "message": "AssertionError: expected 404 to equal 410",
                "estack": "AssertionError: expected 404 to equal 410\n    at Context.eval (http://localhost:38053/__cypress/tests?p=cypress/integration/uniresolver_spec.js:232:40)",
                "diff": "- 404\n+ 410\n"
              },
              "uuid": "4a2ad1e8-936d-43e7-bdb0-1c593b94c16a",
              "parentUUID": "04bc34cd-a165-4f7a-a895-c74643204ea3",
              "isHook": false,
              "skipped": false
            }
          ],
          "suites": [],
          "passes": [],
          "failures": [
            "4a2ad1e8-936d-43e7-bdb0-1c593b94c16a"
          ],
          "pending": [],
          "skipped": [],
          "duration": 81,
          "root": false,
          "rootEmpty": false,
          "_timeout": 2000
        },
        {
          "uuid": "6f47f38e-dde8-4d45-85bc-25b54f1a7430",
          "title": "Test Scenario 5: Not found",
          "fullFile": "",
          "file": "",
          "beforeHooks": [],
          "afterHooks": [],
          "tests": [
            {
              "title": "Returns an HTTP code of 404 for non-existent DIDs",
              "fullTitle": "Test Scenario 5: Not found Returns an HTTP code of 404 for non-existent DIDs",
              "timedOut": null,
              "duration": 70,
              "state": "failed",
              "speed": null,
              "pass": false,
              "fail": true,
              "pending": false,
              "context": null,
              "code": "cy.fixture(path_example_dids).its(\"nonExisDids\").then(list => {\n  Object.keys(list).forEach(key => {\n    const nonExDid = list[key];\n    cy.request({\n      method: \"GET\",\n      url: endpoint + nonExDid,\n      failOnStatusCode: false\n    }).then(response => {\n      expect(response.status).to.eq(404);\n      expect(response.headers[\"content-type\"]).to.contain('application/ld+json;profile=\"https://w3id.org/did-resolution\"');\n      expect(response).to.be.a(\"object\");\n      expect(response.body.didResolutionMetadata.error).to.eq(\"notFound\");\n    });\n  });\n});",
              "err": {
                "message": "AssertionError: expected 501 to equal 404",
                "estack": "AssertionError: expected 501 to equal 404\n    at Context.eval (http://localhost:38053/__cypress/tests?p=cypress/integration/uniresolver_spec.js:254:40)",
                "diff": "- 501\n+ 404\n"
              },
              "uuid": "83c1d1c5-a9af-4b98-8970-46ba5b963624",
              "parentUUID": "6f47f38e-dde8-4d45-85bc-25b54f1a7430",
              "isHook": false,
              "skipped": false
            }
          ],
          "suites": [],
          "passes": [],
          "failures": [
            "83c1d1c5-a9af-4b98-8970-46ba5b963624"
          ],
          "pending": [],
          "skipped": [],
          "duration": 70,
          "root": false,
          "rootEmpty": false,
          "_timeout": 2000
        },
        {
          "uuid": "c88638ad-d516-419b-a278-d4bdf1abe5d1",
          "title": "Test Scenario 6A: Invalid DID",
          "fullFile": "",
          "file": "",
          "beforeHooks": [],
          "afterHooks": [],
          "tests": [
            {
              "title": "Returns a HTTP code of 400 for an invalid DID",
              "fullTitle": "Test Scenario 6A: Invalid DID Returns a HTTP code of 400 for an invalid DID",
              "timedOut": null,
              "duration": 117,
              "state": "passed",
              "speed": "fast",
              "pass": true,
              "fail": false,
              "pending": false,
              "context": null,
              "code": "cy.fixture(path_example_dids).its(\"invalidDids\").then(list => {\n  Object.keys(list).forEach(key => {\n    const invalidDid = list[key];\n    cy.request({\n      method: \"GET\",\n      url: endpoint + invalidDid,\n      failOnStatusCode: false\n    }).then(response => {\n      expect(response.status).to.eq(400);\n      expect(response.headers[\"content-type\"]).to.contain('application/ld+json;profile=\"https://w3id.org/did-resolution\"');\n      expect(response).to.be.a(\"object\");\n      expect(response.body.didResolutionMetadata.error).contains(\"invalidDid\");\n    });\n  });\n});",
              "err": {},
              "uuid": "dd571bf4-f41a-47ab-a274-da56e2eec373",
              "parentUUID": "c88638ad-d516-419b-a278-d4bdf1abe5d1",
              "isHook": false,
              "skipped": false
            }
          ],
          "suites": [],
          "passes": [
            "dd571bf4-f41a-47ab-a274-da56e2eec373"
          ],
          "failures": [],
          "pending": [],
          "skipped": [],
          "duration": 117,
          "root": false,
          "rootEmpty": false,
          "_timeout": 2000
        },
        {
          "uuid": "a038ea52-ba91-4aca-8cba-7f0fc04c547c",
          "title": "Test Scenario 6B: method not supported DIDs",
          "fullFile": "",
          "file": "",
          "beforeHooks": [],
          "afterHooks": [],
          "tests": [
            {
              "title": "Raises an error for unsupported DID methods",
              "fullTitle": "Test Scenario 6B: method not supported DIDs Raises an error for unsupported DID methods",
              "timedOut": null,
              "duration": 56,
              "state": "failed",
              "speed": null,
              "pass": false,
              "fail": true,
              "pending": false,
              "context": null,
              "code": "cy.fixture(path_example_dids).its(\"methodNotSupportedDids\").then(list => {\n  Object.keys(list).forEach(key => {\n    const invalidDid = list[key];\n    cy.request({\n      method: \"GET\",\n      url: endpoint + invalidDid,\n      failOnStatusCode: false\n    }).then(response => {\n      expect(response.body.didResolutionMetadata.error).contains(\"methodNotSupported\");\n      expect(response).to.be.a(\"object\"); // todo: should this be 404 or 400?\n      expect(response.status).to.eq(400); // returns 501\n      expect(response.headers[\"content-type\"]).to.contain('application/ld+json;profile=\"https://w3id.org/did-resolution\"');\n    });\n  });\n});",
              "err": {
                "message": "AssertionError: expected 501 to equal 400",
                "estack": "AssertionError: expected 501 to equal 400\n    at Context.eval (http://localhost:38053/__cypress/tests?p=cypress/integration/uniresolver_spec.js:301:40)",
                "diff": "- 501\n+ 400\n"
              },
              "uuid": "43c1ecba-1272-4e0c-9c9b-b8f24fff3577",
              "parentUUID": "a038ea52-ba91-4aca-8cba-7f0fc04c547c",
              "isHook": false,
              "skipped": false
            }
          ],
          "suites": [],
          "passes": [],
          "failures": [
            "43c1ecba-1272-4e0c-9c9b-b8f24fff3577"
          ],
          "pending": [],
          "skipped": [],
          "duration": 56,
          "root": false,
          "rootEmpty": false,
          "_timeout": 2000
        },
        {
          "uuid": "e3e9edca-5f77-442e-8a60-8d6baf8dee51",
          "title": "Test Scenario 6C: invalid verificationMethod.id",
          "fullFile": "",
          "file": "",
          "beforeHooks": [],
          "afterHooks": [],
          "tests": [
            {
              "title": "Raises error when verificationMethod.id is invalid",
              "fullTitle": "Test Scenario 6C: invalid verificationMethod.id Raises error when verificationMethod.id is invalid",
              "timedOut": null,
              "duration": 885,
              "state": "failed",
              "speed": null,
              "pass": false,
              "fail": true,
              "pending": false,
              "context": null,
              "code": "cy.fixture(path_example_dids).its(\"invalidVerificationMethodId\").then(list => {\n  Object.keys(list).forEach(key => {\n    const invalidDid = list[key];\n    cy.request({\n      method: \"GET\",\n      url: endpoint + invalidDid,\n      failOnStatusCode: false\n    }).then(response => {\n      expect(response).to.be.a(\"object\");\n      expect(response.headers[\"content-type\"]).to.contain('application/ld+json;profile=\"https://w3id.org/did-resolution\"'); // todo: should this be 404 or 400?\n      expect(response.status).to.eq(400); // return 200\n      expect(response.body.didResolutionMetadata.error).contains(\"invalidDidUrl\"); // doesn't exist\n    });\n  });\n});",
              "err": {
                "message": "AssertionError: expected 200 to equal 400",
                "estack": "AssertionError: expected 200 to equal 400\n    at Context.eval (http://localhost:38053/__cypress/tests?p=cypress/integration/uniresolver_spec.js:326:40)",
                "diff": "- 200\n+ 400\n"
              },
              "uuid": "df0b4a81-0a95-4d6a-8286-c67a256f5a00",
              "parentUUID": "e3e9edca-5f77-442e-8a60-8d6baf8dee51",
              "isHook": false,
              "skipped": false
            }
          ],
          "suites": [],
          "passes": [],
          "failures": [
            "df0b4a81-0a95-4d6a-8286-c67a256f5a00"
          ],
          "pending": [],
          "skipped": [],
          "duration": 885,
          "root": false,
          "rootEmpty": false,
          "_timeout": 2000
        },
        {
          "uuid": "14c276fb-ea22-4a18-bc85-c59676d27868",
          "title": "Test Scenario 6D: invalid verificationMethod.controller",
          "fullFile": "",
          "file": "",
          "beforeHooks": [],
          "afterHooks": [],
          "tests": [
            {
              "title": "Raises error when verificationMethod.controller is invalid",
              "fullTitle": "Test Scenario 6D: invalid verificationMethod.controller Raises error when verificationMethod.controller is invalid",
              "timedOut": null,
              "duration": 194,
              "state": "failed",
              "speed": null,
              "pass": false,
              "fail": true,
              "pending": false,
              "context": null,
              "code": "cy.fixture(path_example_dids).its(\"invalidVerificationMethodController\").then(list => {\n  Object.keys(list).forEach(key => {\n    const invalidDid = list[key];\n    cy.request({\n      method: \"GET\",\n      url: endpoint + invalidDid,\n      failOnStatusCode: false\n    }).then(response => {\n      expect(response).to.be.a(\"object\");\n      expect(response.headers[\"content-type\"]).to.contain('application/ld+json;profile=\"https://w3id.org/did-resolution\"'); // todo: should this be 404 or 400?\n      expect(response.status).to.eq(400); // returns 200\n      expect(response.body.didResolutionMetadata.error).contains(\"invalidDid\"); // doesn't exist\n    });\n  });\n});",
              "err": {
                "message": "AssertionError: expected 200 to equal 400",
                "estack": "AssertionError: expected 200 to equal 400\n    at Context.eval (http://localhost:38053/__cypress/tests?p=cypress/integration/uniresolver_spec.js:350:40)",
                "diff": "- 200\n+ 400\n"
              },
              "uuid": "e8a76a69-d9b0-4783-b4aa-53fe7fc874f4",
              "parentUUID": "14c276fb-ea22-4a18-bc85-c59676d27868",
              "isHook": false,
              "skipped": false
            }
          ],
          "suites": [],
          "passes": [],
          "failures": [
            "e8a76a69-d9b0-4783-b4aa-53fe7fc874f4"
          ],
          "pending": [],
          "skipped": [],
          "duration": 194,
          "root": false,
          "rootEmpty": false,
          "_timeout": 2000
        },
        {
          "uuid": "3b5ffc49-a057-401b-b038-0c377562bdf0",
          "title": "Test Scenario 6E: invalid didDocument.id",
          "fullFile": "",
          "file": "",
          "beforeHooks": [],
          "afterHooks": [],
          "tests": [
            {
              "title": "Raises error when didDocument.id is invalid",
              "fullTitle": "Test Scenario 6E: invalid didDocument.id Raises error when didDocument.id is invalid",
              "timedOut": null,
              "duration": 71,
              "state": "passed",
              "speed": "fast",
              "pass": true,
              "fail": false,
              "pending": false,
              "context": null,
              "code": "cy.fixture(path_example_dids).its(\"invalidDidDocumentId\").then(list => {\n  Object.keys(list).forEach(key => {\n    const invalidDid = list[key];\n    cy.request({\n      method: \"GET\",\n      url: endpoint + invalidDid,\n      failOnStatusCode: false\n    }).then(response => {\n      expect(response).to.be.a(\"object\");\n      expect(response.headers[\"content-type\"]).to.contain('application/ld+json;profile=\"https://w3id.org/did-resolution\"');\n      expect(response.status).to.eq(400);\n      expect(response.body.didResolutionMetadata.error).contains(\"invalidDid\");\n    });\n  });\n});",
              "err": {},
              "uuid": "3691fe88-f92d-4946-8601-eedfc2d8acd6",
              "parentUUID": "3b5ffc49-a057-401b-b038-0c377562bdf0",
              "isHook": false,
              "skipped": false
            }
          ],
          "suites": [],
          "passes": [
            "3691fe88-f92d-4946-8601-eedfc2d8acd6"
          ],
          "failures": [],
          "pending": [],
          "skipped": [],
          "duration": 71,
          "root": false,
          "rootEmpty": false,
          "_timeout": 2000
        },
        {
          "uuid": "3170af18-936b-4d6b-9829-d7562894cdc0",
          "title": "Test Scenario 6F: Invalid didDocument scheme",
          "fullFile": "",
          "file": "",
          "beforeHooks": [],
          "afterHooks": [],
          "tests": [
            {
              "title": "Raises invalidDid error when if scheme is not did",
              "fullTitle": "Test Scenario 6F: Invalid didDocument scheme Raises invalidDid error when if scheme is not did",
              "timedOut": null,
              "duration": 71,
              "state": "passed",
              "speed": "fast",
              "pass": true,
              "fail": false,
              "pending": false,
              "context": null,
              "code": "cy.fixture(path_example_dids).its(\"invalidDidScheme\").then(list => {\n  Object.keys(list).forEach(key => {\n    const invalidDid = list[key];\n    cy.request({\n      method: \"GET\",\n      url: endpoint + invalidDid,\n      failOnStatusCode: false\n    }).then(response => {\n      expect(response).to.be.a(\"object\");\n      expect(response.headers[\"content-type\"]).to.contain('application/ld+json;profile=\"https://w3id.org/did-resolution\"');\n      expect(response.status).to.eq(400);\n      expect(response.body.didResolutionMetadata.error).contains(\"invalidDid\");\n    });\n  });\n});",
              "err": {},
              "uuid": "ac481422-b1eb-410b-b709-15e638eb0dc1",
              "parentUUID": "3170af18-936b-4d6b-9829-d7562894cdc0",
              "isHook": false,
              "skipped": false
            }
          ],
          "suites": [],
          "passes": [
            "ac481422-b1eb-410b-b709-15e638eb0dc1"
          ],
          "failures": [],
          "pending": [],
          "skipped": [],
          "duration": 71,
          "root": false,
          "rootEmpty": false,
          "_timeout": 2000
        },
        {
          "uuid": "66971e85-9193-4e02-8b81-ac5b0165ee36",
          "title": "Test Scenario 6G: notAllowedLocalDerivedKey error/warning",
          "fullFile": "",
          "file": "",
          "beforeHooks": [],
          "afterHooks": [],
          "tests": [
            {
              "title": "Raises notAllowedLocalDerivedKey error when did is incorrect",
              "fullTitle": "Test Scenario 6G: notAllowedLocalDerivedKey error/warning Raises notAllowedLocalDerivedKey error when did is incorrect",
              "timedOut": null,
              "duration": 627,
              "state": "failed",
              "speed": null,
              "pass": false,
              "fail": true,
              "pending": false,
              "context": null,
              "code": "cy.fixture(path_example_dids).its(\"notAllowedLocalDerivedKey\").then(list => {\n  Object.keys(list).forEach(key => {\n    const invalidDid = list[key];\n    cy.request({\n      method: \"GET\",\n      url: endpoint + invalidDid,\n      failOnStatusCode: false\n    }).then(response => {\n      expect(response).to.be.a(\"object\");\n      expect(response.headers[\"content-type\"]).to.contain('application/ld+json;profile=\"https://w3id.org/did-resolution\"');\n      expect(response.status).to.eq(400);\n      expect(response.body.didResolutionMetadata.error).contains(\"notAllowedLocalDerivedKey\");\n    });\n  });\n});",
              "err": {
                "message": "AssertionError: expected 200 to equal 400",
                "estack": "AssertionError: expected 200 to equal 400\n    at Context.eval (http://localhost:38053/__cypress/tests?p=cypress/integration/uniresolver_spec.js:417:40)",
                "diff": "- 200\n+ 400\n"
              },
              "uuid": "201ba7ca-b4e6-4c78-9423-1fff73c71c81",
              "parentUUID": "66971e85-9193-4e02-8b81-ac5b0165ee36",
              "isHook": false,
              "skipped": false
            }
          ],
          "suites": [],
          "passes": [],
          "failures": [
            "201ba7ca-b4e6-4c78-9423-1fff73c71c81"
          ],
          "pending": [],
          "skipped": [],
          "duration": 627,
          "root": false,
          "rootEmpty": false,
          "_timeout": 2000
        },
        {
          "uuid": "4daea226-dfbf-4ec0-b84d-e473213567d3",
          "title": "Test Scenario 6H: notAllowedLocalDuplicateKey error/warning",
          "fullFile": "",
          "file": "",
          "beforeHooks": [],
          "afterHooks": [],
          "tests": [
            {
              "title": "Raises notAllowedLocalDuplicateKey error when did is incorrect",
              "fullTitle": "Test Scenario 6H: notAllowedLocalDuplicateKey error/warning Raises notAllowedLocalDuplicateKey error when did is incorrect",
              "timedOut": null,
              "duration": 54,
              "state": "failed",
              "speed": null,
              "pass": false,
              "fail": true,
              "pending": false,
              "context": null,
              "code": "cy.fixture(path_example_dids).its(\"invalidDidDocumentId\").then(list => {\n  Object.keys(list).forEach(key => {\n    const invalidDid = list[key];\n    cy.request({\n      method: \"GET\",\n      url: endpoint + invalidDid,\n      failOnStatusCode: false\n    }).then(response => {\n      expect(response).to.be.a(\"object\");\n      expect(response.headers[\"content-type\"]).to.contain('application/ld+json;profile=\"https://w3id.org/did-resolution\"');\n      expect(response.status).to.eq(400);\n      expect(response.body.didResolutionMetadata.error).contains(\"notAllowedLocalDuplicateKey\");\n    });\n  });\n});",
              "err": {
                "message": "AssertionError: expected 'invalidDid' to include 'notAllowedLocalDuplicateKey'",
                "estack": "AssertionError: expected 'invalidDid' to include 'notAllowedLocalDuplicateKey'\n    at Context.eval (http://localhost:38053/__cypress/tests?p=cypress/integration/uniresolver_spec.js:440:63)",
                "diff": null
              },
              "uuid": "a75720e7-d1f8-42ac-b13f-fc21aba53ad5",
              "parentUUID": "4daea226-dfbf-4ec0-b84d-e473213567d3",
              "isHook": false,
              "skipped": false
            }
          ],
          "suites": [],
          "passes": [],
          "failures": [
            "a75720e7-d1f8-42ac-b13f-fc21aba53ad5"
          ],
          "pending": [],
          "skipped": [],
          "duration": 54,
          "root": false,
          "rootEmpty": false,
          "_timeout": 2000
        },
        {
          "uuid": "d3c5bee6-8d27-4abe-ba52-1769ba8b2bdd",
          "title": "Test Scenario 6I: notAllowedKeyType error/warning",
          "fullFile": "",
          "file": "",
          "beforeHooks": [],
          "afterHooks": [],
          "tests": [
            {
              "title": "Raises notAllowedKeyType error when did is incorrect",
              "fullTitle": "Test Scenario 6I: notAllowedKeyType error/warning Raises notAllowedKeyType error when did is incorrect",
              "timedOut": null,
              "duration": 76,
              "state": "failed",
              "speed": null,
              "pass": false,
              "fail": true,
              "pending": false,
              "context": null,
              "code": "cy.fixture(path_example_dids).its(\"invalidDidDocumentId\").then(list => {\n  Object.keys(list).forEach(key => {\n    const invalidDid = list[key];\n    cy.request({\n      method: \"GET\",\n      url: endpoint + invalidDid,\n      failOnStatusCode: false\n    }).then(response => {\n      expect(response).to.be.a(\"object\");\n      expect(response.headers[\"content-type\"]).to.contain('application/ld+json;profile=\"https://w3id.org/did-resolution\"');\n      expect(response.status).to.eq(400);\n      expect(response.body.didResolutionMetadata.error).contains(\"notAllowedKeyType\");\n    });\n  });\n});",
              "err": {
                "message": "AssertionError: expected 'invalidDid' to include 'notAllowedKeyType'",
                "estack": "AssertionError: expected 'invalidDid' to include 'notAllowedKeyType'\n    at Context.eval (http://localhost:38053/__cypress/tests?p=cypress/integration/uniresolver_spec.js:462:63)",
                "diff": null
              },
              "uuid": "3bc8f3da-238e-44ab-9906-6349b6752c69",
              "parentUUID": "d3c5bee6-8d27-4abe-ba52-1769ba8b2bdd",
              "isHook": false,
              "skipped": false
            }
          ],
          "suites": [],
          "passes": [],
          "failures": [
            "3bc8f3da-238e-44ab-9906-6349b6752c69"
          ],
          "pending": [],
          "skipped": [],
          "duration": 76,
          "root": false,
          "rootEmpty": false,
          "_timeout": 2000
        },
        {
          "uuid": "9eb846a2-796d-4329-8610-13b9a77a2a25",
          "title": "Test Scenario 6J: notAllowedMethod error/warning",
          "fullFile": "",
          "file": "",
          "beforeHooks": [],
          "afterHooks": [],
          "tests": [
            {
              "title": "Raises notAllowedMethod error when did is incorrect",
              "fullTitle": "Test Scenario 6J: notAllowedMethod error/warning Raises notAllowedMethod error when did is incorrect",
              "timedOut": null,
              "duration": 63,
              "state": "failed",
              "speed": null,
              "pass": false,
              "fail": true,
              "pending": false,
              "context": null,
              "code": "cy.fixture(path_example_dids).its(\"notAllowedMethod\").then(list => {\n  Object.keys(list).forEach(key => {\n    const invalidDid = list[key];\n    cy.request({\n      method: \"GET\",\n      url: endpoint + invalidDid,\n      failOnStatusCode: false\n    }).then(response => {\n      expect(response).to.be.a(\"object\");\n      expect(response.headers[\"content-type\"]).to.contain('application/ld+json;profile=\"https://w3id.org/did-resolution\"');\n      expect(response.status).to.eq(400);\n      expect(response.body.didResolutionMetadata.error).contains(\"notAllowedMethod\");\n    });\n  });\n});",
              "err": {
                "message": "AssertionError: expected 404 to equal 400",
                "estack": "AssertionError: expected 404 to equal 400\n    at Context.eval (http://localhost:38053/__cypress/tests?p=cypress/integration/uniresolver_spec.js:484:40)",
                "diff": "- 404\n+ 400\n"
              },
              "uuid": "1fb130ab-cfee-4cc7-b464-f9dc4a5249a4",
              "parentUUID": "9eb846a2-796d-4329-8610-13b9a77a2a25",
              "isHook": false,
              "skipped": false
            }
          ],
          "suites": [],
          "passes": [],
          "failures": [
            "1fb130ab-cfee-4cc7-b464-f9dc4a5249a4"
          ],
          "pending": [],
          "skipped": [],
          "duration": 63,
          "root": false,
          "rootEmpty": false,
          "_timeout": 2000
        },
        {
          "uuid": "e09fcd1b-4cb8-4993-a2b5-d7eb88c57109",
          "title": "Test Scenario 7: DID URLs with fragments",
          "fullFile": "",
          "file": "",
          "beforeHooks": [],
          "afterHooks": [],
          "tests": [
            {
              "title": "Can resolve a DID with a fragment",
              "fullTitle": "Test Scenario 7: DID URLs with fragments Can resolve a DID with a fragment",
              "timedOut": null,
              "duration": 74,
              "state": "failed",
              "speed": null,
              "pass": false,
              "fail": true,
              "pending": false,
              "context": null,
              "code": "cy.fixture(path_example_dids).its(\"fragmentDids\").then(list => {\n  Object.keys(list).forEach(key => {\n    const fragmentDid = list[key];\n    cy.request({\n      method: \"GET\",\n      url: endpoint + fragmentDid,\n      failOnStatusCode: false,\n      headers: {\n        Accept: \"application/did+ld+json\",\n        Authorization: \"Bearer b082c420-df67-4b06-899c-b7c51d75fba0\"\n      }\n    }).as(\"request\");\n    cy.get(\"@request\").then(response => {\n      expect(response.status).to.eq(200);\n      expect(response.headers[\"content-type\"]).to.contain(\"application/did+ld+json\");\n      expect(response.body).not.to.have.property(\"didDocument\");\n      expect(response.body).to.have.property(\"id\");\n      expect(response.body[\"id\"]).to.contain(decodeURIComponent(fragmentDid.split(\"#\")[0]));\n    });\n  });\n});",
              "err": {
                "message": "AssertionError: expected 400 to equal 200",
                "estack": "AssertionError: expected 400 to equal 200\n    at Context.eval (http://localhost:38053/__cypress/tests?p=cypress/integration/uniresolver_spec.js:509:40)",
                "diff": "- 400\n+ 200\n"
              },
              "uuid": "23f499cb-a47c-482e-8317-1cdfd3a65126",
              "parentUUID": "e09fcd1b-4cb8-4993-a2b5-d7eb88c57109",
              "isHook": false,
              "skipped": false
            }
          ],
          "suites": [],
          "passes": [],
          "failures": [
            "23f499cb-a47c-482e-8317-1cdfd3a65126"
          ],
          "pending": [],
          "skipped": [],
          "duration": 74,
          "root": false,
          "rootEmpty": false,
          "_timeout": 2000
        },
        {
          "uuid": "d51425fe-b8f9-4d94-9c61-167243ddedce",
          "title": "Test Scenario 8: Service and relativeRef parameters",
          "fullFile": "",
          "file": "",
          "beforeHooks": [],
          "afterHooks": [],
          "tests": [
            {
              "title": "Fetches DID",
              "fullTitle": "Test Scenario 8: Service and relativeRef parameters Fetches DID",
              "timedOut": null,
              "duration": 74,
              "state": "passed",
              "speed": "fast",
              "pass": true,
              "fail": false,
              "pending": false,
              "context": null,
              "code": "cy.fixture(path_example_dids).its(\"relativeParamDids\").then(list => {\n  Object.keys(list).forEach(key => {\n    const fragmentDid = list[key];\n    console.log(\"FRAGMENT DID IS\", fragmentDid);\n    cy.request({\n      method: \"GET\",\n      url: endpoint + fragmentDid,\n      headers: {\n        Accept: \"text/uri-list\"\n      },\n      failOnStatusCode: false\n    }).as(\"response\");\n    it(\"MUST return HTTP response status equals 303\", () => {\n      cy.get(\"@response\").then(response => {\n        expect(response.status).to.eq(303);\n      });\n    });\n  });\n});",
              "err": {},
              "uuid": "7b20f40c-3533-4bd4-ae1c-d184e54b298f",
              "parentUUID": "d51425fe-b8f9-4d94-9c61-167243ddedce",
              "isHook": false,
              "skipped": false
            }
          ],
          "suites": [],
          "passes": [
            "7b20f40c-3533-4bd4-ae1c-d184e54b298f"
          ],
          "failures": [],
          "pending": [],
          "skipped": [],
          "duration": 74,
          "root": false,
          "rootEmpty": false,
          "_timeout": 2000
        },
        {
          "uuid": "04906fa7-c929-477b-94e5-001f7864f786",
          "title": "Test Scenario 9: DID URLs with transformKeys",
          "fullFile": "",
          "file": "",
          "beforeHooks": [],
          "afterHooks": [],
          "tests": [
            {
              "title": "MUST return HTTP response status 200",
              "fullTitle": "Test Scenario 9: DID URLs with transformKeys MUST return HTTP response status 200",
              "timedOut": null,
              "duration": 50,
              "state": "failed",
              "speed": null,
              "pass": false,
              "fail": true,
              "pending": false,
              "context": null,
              "code": "cy.fixture(path_example_dids).its(\"transformKeyDids\").then(list => {\n  Object.keys(list).forEach(key => {\n    const transformKeyDid = list[key];\n    cy.request({\n      method: \"GET\",\n      url: endpoint + transformKeyDid,\n      headers: {\n        Accept: \"application/did+ld+json\",\n        Authorization: \"Bearer b082c420-df67-4b06-899c-b7c51d75fba0\"\n      },\n      failOnStatusCode: false\n    }).as(\"request\");\n    cy.get(\"@request\").then(response => {\n      expect(response.status).to.eq(200);\n      expect(response).to.be.a(\"object\");\n      response.body.verificationMethod.forEach(out => {\n        expect(out).has.property(\"type\").to.be.oneOf([\"JsonWebKey2020\", \"Ed25519VerificationKey2018\", \"X25519KeyAgreementKey2019\"]);\n      });\n      expect(response.headers[\"content-type\"]).contains(\"application/did+ld+json\");\n      expect(response.body).has.property(\"id\", decodeURIComponent(transformKeyDid.split(\"?\")[0].split(\"#\")[0]));\n    });\n  });\n});",
              "err": {
                "message": "AssertionError: expected 400 to equal 200",
                "estack": "AssertionError: expected 400 to equal 200\n    at Context.eval (http://localhost:38053/__cypress/tests?p=cypress/integration/uniresolver_spec.js:564:40)",
                "diff": "- 400\n+ 200\n"
              },
              "uuid": "ab3a5252-a8ac-4abb-875e-51f3de31dd0c",
              "parentUUID": "04906fa7-c929-477b-94e5-001f7864f786",
              "isHook": false,
              "skipped": false
            }
          ],
          "suites": [],
          "passes": [],
          "failures": [
            "ab3a5252-a8ac-4abb-875e-51f3de31dd0c"
          ],
          "pending": [],
          "skipped": [],
          "duration": 50,
          "root": false,
          "rootEmpty": false,
          "_timeout": 2000
        },
        {
          "uuid": "65d18e96-207e-4abb-afa4-cca58e7f8e0e",
          "title": "Test Scenario 10: DID URLs with versionTime parameter",
          "fullFile": "",
          "file": "",
          "beforeHooks": [],
          "afterHooks": [],
          "tests": [
            {
              "title": "MUST return HTTP response status 200",
              "fullTitle": "Test Scenario 10: DID URLs with versionTime parameter MUST return HTTP response status 200",
              "timedOut": null,
              "duration": 80,
              "state": "failed",
              "speed": null,
              "pass": false,
              "fail": true,
              "pending": false,
              "context": null,
              "code": "cy.fixture(path_example_dids).its(\"versionTimeDids\").then(list => {\n  Object.keys(list).forEach(key => {\n    const versionTimeDid = list[key];\n    cy.request({\n      method: \"GET\",\n      url: endpoint + versionTimeDid,\n      headers: {\n        Accept: \"application/did+ld+json\",\n        Authorization: \"Bearer b082c420-df67-4b06-899c-b7c51d75fba0\"\n      },\n      failOnStatusCode: false\n    }).as(\"request\");\n    cy.get(\"@request\").then(response => {\n      expect(response.status).to.eq(200);\n      expect(response.headers[\"content-type\"]).contains(\"application/did+ld+json\");\n      expect(response).to.be.a(\"object\");\n      expect(response.body).has.property(\"id\").contains(\"did:sov:DjxRxnL4gXsncbH8jM8ySM\");\n    });\n  });\n});",
              "err": {
                "message": "AssertionError: expected 400 to equal 200",
                "estack": "AssertionError: expected 400 to equal 200\n    at Context.eval (http://localhost:38053/__cypress/tests?p=cypress/integration/uniresolver_spec.js:594:40)",
                "diff": "- 400\n+ 200\n"
              },
              "uuid": "ae029417-9921-4eea-a197-187420118c8e",
              "parentUUID": "65d18e96-207e-4abb-afa4-cca58e7f8e0e",
              "isHook": false,
              "skipped": false
            }
          ],
          "suites": [],
          "passes": [],
          "failures": [
            "ae029417-9921-4eea-a197-187420118c8e"
          ],
          "pending": [],
          "skipped": [],
          "duration": 80,
          "root": false,
          "rootEmpty": false,
          "_timeout": 2000
        },
        {
          "uuid": "afa3ce5f-1279-4686-9623-0c4fe3564f62",
          "title": "Test Scenario 11: DID URLs with versionId parameter",
          "fullFile": "",
          "file": "",
          "beforeHooks": [],
          "afterHooks": [],
          "tests": [
            {
              "title": "MUST return HTTP response status 200",
              "fullTitle": "Test Scenario 11: DID URLs with versionId parameter MUST return HTTP response status 200",
              "timedOut": null,
              "duration": 52,
              "state": "failed",
              "speed": null,
              "pass": false,
              "fail": true,
              "pending": false,
              "context": null,
              "code": "cy.fixture(path_example_dids).its(\"versionIdDids\").then(list => {\n  Object.keys(list).forEach(key => {\n    const versionIdDid = list[key];\n    cy.request({\n      method: \"GET\",\n      url: endpoint + versionIdDid,\n      headers: {\n        Accept: \"application/did+ld+json\",\n        Authorization: \"Bearer b082c420-df67-4b06-899c-b7c51d75fba0\"\n      },\n      failOnStatusCode: false\n    }).as(\"request\");\n    cy.get(\"@request\").then(response => {\n      expect(response.status).to.eq(200);\n      expect(response).to.be.a(\"object\");\n      expect(response.headers[\"content-type\"]).contains(\"application/did+ld+json\");\n      expect(response.body).has.property(\"id\").contains(decodeURIComponent(versionIdDid.split(\"?\")[0]));\n    });\n  });\n});",
              "err": {
                "message": "AssertionError: expected 400 to equal 200",
                "estack": "AssertionError: expected 400 to equal 200\n    at Context.eval (http://localhost:38053/__cypress/tests?p=cypress/integration/uniresolver_spec.js:621:40)",
                "diff": "- 400\n+ 200\n"
              },
              "uuid": "88a65e01-952e-4ea0-b5b9-1d9ce839cd5f",
              "parentUUID": "afa3ce5f-1279-4686-9623-0c4fe3564f62",
              "isHook": false,
              "skipped": false
            }
          ],
          "suites": [],
          "passes": [],
          "failures": [
            "88a65e01-952e-4ea0-b5b9-1d9ce839cd5f"
          ],
          "pending": [],
          "skipped": [],
          "duration": 52,
          "root": false,
          "rootEmpty": false,
          "_timeout": 2000
        },
        {
          "uuid": "2f7a6e24-8322-46ac-9332-36c9081bf212",
          "title": "Test Scenario 12: Resolve a DID / dereference a DID URL",
          "fullFile": "",
          "file": "",
          "beforeHooks": [],
          "afterHooks": [],
          "tests": [
            {
              "title": "MUST return HTTP response status 200",
              "fullTitle": "Test Scenario 12: Resolve a DID / dereference a DID URL MUST return HTTP response status 200",
              "timedOut": null,
              "duration": 180,
              "state": "failed",
              "speed": null,
              "pass": false,
              "fail": true,
              "pending": false,
              "context": null,
              "code": "cy.fixture(path_example_dids).its(\"normalDids\").then(list => {\n  Object.keys(list).forEach(key => {\n    const normalDid = list[key];\n    cy.request({\n      method: \"GET\",\n      url: endpoint + normalDid,\n      headers: {\n        Accept: \"application/json\"\n      },\n      failOnStatusCode: false\n    }).as(\"request\");\n    cy.get(\"@request\").then(response => {\n      console.log(\"normal did is:\", normalDid);\n      expect(response.status).to.eq(200);\n      expect(response.headers[\"content-type\"]).contains(\"application/did+json;charset=utf-8\");\n      expect(response.body).has.property(\"id\", normalDid); // expect(response.body[\"keyAgreement\"][0]).to.contain(normalDid);\n    });\n  });\n});",
              "err": {
                "message": "AssertionError: expected 404 to equal 200",
                "estack": "AssertionError: expected 404 to equal 200\n    at Context.eval (http://localhost:38053/__cypress/tests?p=cypress/integration/uniresolver_spec.js:648:40)",
                "diff": "- 404\n+ 200\n"
              },
              "uuid": "f6d3420f-e577-454d-95e9-dc29b8572b3e",
              "parentUUID": "2f7a6e24-8322-46ac-9332-36c9081bf212",
              "isHook": false,
              "skipped": false
            }
          ],
          "suites": [],
          "passes": [],
          "failures": [
            "f6d3420f-e577-454d-95e9-dc29b8572b3e"
          ],
          "pending": [],
          "skipped": [],
          "duration": 180,
          "root": false,
          "rootEmpty": false,
          "_timeout": 2000
        },
        {
          "uuid": "b0d3a781-cbea-42a3-b9b3-f4697a662fd0",
          "title": "Test Scenario 12B: Resolve a DID / dereference a DID URL",
          "fullFile": "",
          "file": "",
          "beforeHooks": [],
          "afterHooks": [],
          "tests": [
            {
              "title": "MUST return HTTP response status 200",
              "fullTitle": "Test Scenario 12B: Resolve a DID / dereference a DID URL MUST return HTTP response status 200",
              "timedOut": null,
              "duration": 120,
              "state": "failed",
              "speed": null,
              "pass": false,
              "fail": true,
              "pending": false,
              "context": null,
              "code": "cy.fixture(path_example_dids).its(\"normalDids\").then(list => {\n  Object.keys(list).forEach(key => {\n    const normalDid = list[key];\n    cy.request({\n      method: \"GET\",\n      url: endpoint + normalDid,\n      headers: {\n        Accept: 'application/ld+json;profile=\"https://w3c-ccg.github.io/did-resolution/\"'\n      },\n      failOnStatusCode: false\n    }).as(\"request\");\n    cy.get(\"@request\").then(response => {\n      console.log(\"normal did is:\", normalDid);\n      expect(response.status).to.eq(200);\n      expect(response.headers[\"content-type\"]).contains('application/ld+json; profile=\"https://w3c-ccg.github.io/did-resolution/\"');\n    });\n  });\n});",
              "err": {
                "message": "AssertionError: expected 406 to equal 200",
                "estack": "AssertionError: expected 406 to equal 200\n    at Context.eval (http://localhost:38053/__cypress/tests?p=cypress/integration/uniresolver_spec.js:675:40)",
                "diff": "- 406\n+ 200\n"
              },
              "uuid": "69eab27d-a69d-4c36-89ba-e72a6b8b8bbe",
              "parentUUID": "b0d3a781-cbea-42a3-b9b3-f4697a662fd0",
              "isHook": false,
              "skipped": false
            }
          ],
          "suites": [],
          "passes": [],
          "failures": [
            "69eab27d-a69d-4c36-89ba-e72a6b8b8bbe"
          ],
          "pending": [],
          "skipped": [],
          "duration": 120,
          "root": false,
          "rootEmpty": false,
          "_timeout": 2000
        }
      ],
      "passes": [],
      "failures": [],
      "pending": [],
      "skipped": [],
      "duration": 0,
      "root": true,
      "rootEmpty": true,
      "_timeout": 2000
    }
  ],
  "meta": {
    "mocha": {
      "version": "7.0.1"
    },
    "mochawesome": {
      "options": {
        "quiet": false,
        "reportFilename": "mochawesome",
        "saveHtml": false,
        "saveJson": true,
        "consoleReporter": "spec",
        "useInlineDiffs": false,
        "code": true
      },
      "version": "7.1.2"
    },
    "marge": {
      "options": {
        "reportDir": "reports/mocha",
        "configFile": "reporterOpts.json",
        "overwrite": false,
        "html": false,
        "json": true
      },
      "version": "6.1.1"
    }
  }
}